{
  "municipality": "Schin op Geul",
  "generated_at": "2026-03-07T02:29:24.818117+00:00",
  "facility_count": 1,
  "facilities": [
    {
      "uuid": "241e35bc-be67-4ee9-9da0-71017d6a4267",
      "name": "P+R Baanweg (Schin op Geul)",
      "operator": "Nederlandse Spoorwegen",
      "street": "",
      "houseNumber": "",
      "zipcode": "",
      "city": "",
      "province": "",
      "latitude": 50.85573,
      "longitude": 5.874163,
      "capacity": 48,
      "vacantSpaces": 48,
      "occupancyPercent": 0.0,
      "open": true,
      "full": false,
      "lastUpdated": 1639497704,
      "minimumHeightInMeters": null,
      "chargingPointCapacity": 0,
      "disabledAccess": false,
      "usage": ""
    }
  ]
}