{
  "municipality": "Zaanstad",
  "generated_at": "2026-03-07T11:26:58.035222+00:00",
  "facility_count": 1,
  "facilities": [
    {
      "uuid": "b3b3f9ec-e94e-4923-8865-53c9c5f7aeaf",
      "name": "Parkeerterrein de Burcht (Zaanstad)",
      "operator": "Zaanstad",
      "street": "",
      "houseNumber": "",
      "zipcode": "",
      "city": "",
      "province": "",
      "latitude": 52.43872,
      "longitude": 4.828007,
      "capacity": 236,
      "vacantSpaces": 236,
      "occupancyPercent": 0.0,
      "open": true,
      "full": false,
      "lastUpdated": 1772882730,
      "minimumHeightInMeters": null,
      "chargingPointCapacity": 0,
      "disabledAccess": false,
      "usage": ""
    }
  ]
}